Workbook
Name AfterRetirement: 'Retirement planner'!$B1>=DesiredRetirementAge
Name Age: IF(PlanYear<=PlanYears,PlanYear-1+YourCurrentAge,NA())
Name AnnualPenionsBenefitsAtRetirement: 'Retirement planner'!$G$6
Name AnnualPensionBenefitAfterRetirementIncreasesPercentage: 'Retirement planner'!$G$7
Name AnnualPensionBenefitAmountUncertaintyPercentage: 'Retirement planner'!$J$9
Name AnnualPensionCenefitIncreasesUncertaintyPercentage: 'Retirement planner'!$J$10
Name AnnualSavingsAmountUncertaintyPercentage: 'Retirement planner'!$J$7
Name AnnualSavingsIncreasesUncertaintyPercentage: 'Retirement planner'!$J$8
Name Balance: IF(PlanYear<=PlanYears,Calculations!$I1048576,NA())
Name Balance_Over: IF(PlanYear<=PlanYears,Calculations!$Y1048576,NA())
Name Balance_Under: IF(PlanYear<=PlanYears,Calculations!$Q1048576,NA())
Name BeforeRetirement: 'Retirement planner'!$B1<DesiredRetirementAge
Name ColumnTitleRegion1..I114.1: 'Retirement planner'!$B$14
Name CurrentAnnualIncome: 'Retirement planner'!$D$7
Name CurrentAnnualIncomeIncreasesPercentage: 'Retirement planner'!$D$8
Name CurrentAnnualSavingsAmount: 'Retirement planner'!$D$10
Name CurrentAnnualSavingsAmount_Over: CurrentAnnualSavingsAmount+CurrentAnnualSavingsAmount*AnnualSavingsAmountUncertaintyPercentage/2
Name CurrentAnnualSavingsAmount_Under: CurrentAnnualSavingsAmount-CurrentAnnualSavingsAmount*AnnualSavingsAmountUncertaintyPercentage/2
Name CurrentAnnualSavingsIncreasesPercentage: 'Retirement planner'!$D$11
Name CurrentRetirementSavingsBalance: 'Retirement planner'!$D$9
Name DesiredRetirementAge: 'Retirement planner'!$G$8
Name DesiredRetirementIncome: IF(PlanYear<=PlanYears,AfterRetirement*IncomeReplacementAtRetirementPercentage*CurrentAnnualIncome*(1+CurrentAnnualIncomeIncreasesPercentage)^(Calculations!$B1-Calculations!$B$15),NA())
Name EndBalance: IF(PlanYear<=PlanYears,Calculations!XEZ1+Calculations!XFA1+Calculations!XFB1-Calculations!XFC1+Calculations!XFD1,NA())
Name IncomeReplacementAtRetirementPercentage: 'Retirement planner'!$G$10
Name Interest: IF(PlanYear<=PlanYears,(Calculations!XFD1*BeforeRetirement*InvestmentReturnPreRetirementPercentage)+(Calculations!XFD1*AfterRetirement*InvestmentReturnPostRetirementPercentage),NA())
Name InvestmentReturnPostRetirementPercentage: 'Retirement planner'!$G$11
Name InvestmentReturnPreRetirementPercentage: 'Retirement planner'!$D$12
Name InvestmentReturnUncertaintyPercentage: 'Retirement planner'!$J$6
Name LastRow: COUNTIF('Retirement planner'!$B$14:$B$59,">1")+35
Name PensionIncome: IF(PlanYear<=PlanYears,AfterRetirement*PensionIncomeInflated,NA())
Name PensionIncome_Over: IF(PlanYear<=PlanYears,AfterRetirement*PensionIncomeInflated_Over,NA())
Name PensionIncome_Under: IF(PlanYear<=PlanYears,AfterRetirement*PensionIncomeInflated_Under,NA())
Name PensionIncomeInflated: AnnualPenionsBenefitsAtRetirement*(1+AnnualPensionBenefitAfterRetirementIncreasesPercentage)^(Calculations!$B1-DesiredRetirementAge)
Name PlanYear: ROWS(Calculations!$B$15:$B1)
Name PlanYears: YearsOfRetirementIncome+(DesiredRetirementAge-YourCurrentAge)
Name Print_Area_Reset: OFFSET('Retirement planner'!$A$1:$O$60,0,0,LastRow)
Name ResultsDisplay_Failure: Calculations!$I$6
Name ResultsDisplay_Failure_1: Calculations!$I$9
Name ResultsDisplay_Failure_2: Calculations!$I$10
Name ResultsDisplay_Failure_3: Calculations!$I$11
Name ResultsDisplay_Failure_4: Calculations!$I$12
Name ResultsDisplay_Success: Calculations!$I$7
Name ResultsDisplay_Success_1: Calculations!$G$9
Name ResultsDisplay_Success_2: Calculations!$G$10
Name ResultsDisplay_Success_3: Calculations!$G$11
Name ResultsDisplay_Success_4: Calculations!$G$12
Name ResultsDisplay_Success_5: Calculations!$G$13
Name RowTitleRegion1..D12: 'Retirement planner'!$B$6
Name RowTitleRegion2..G11: 'Retirement planner'!$E$6
Name RowTitleRegion3..J10: 'Retirement planner'!$H$6
Name Salary: IF(PlanYear<=PlanYears,BeforeRetirement*(Calculations!$C1048576+Calculations!$C1048576*CurrentAnnualIncomeIncreasesPercentage),NA())
Name SavingsBalance_Disbursements: Calculations!$G$15:INDEX(Calculations!$G$15:$G$114,PlanYears)
Name SavingsBalance_RetiredPeriod: Calculations!$AC$15:INDEX(Calculations!$AC$15:$AC$114,PlanYears)
Name SavingsBalance_WorkingPeriod: Calculations!$AB$15:INDEX(Calculations!$AB$15:$AB$114,PlanYears)
Name Success: Calculations!$E$8
Name UncertaintyCone_Over: Calculations!$AF$15:INDEX(Calculations!$AF$15:$AF$114,PlanYears)
Name UncertaintyCone_Under: Calculations!$Q$15:INDEX(Calculations!$Q$15:$Q$114,PlanYears)
Name YearlySavings: IF(PlanYear<=PlanYears,BeforeRetirement*YearlySavingsInflated,NA())
Name YearlySavings_Over: IF(PlanYear<=PlanYears,BeforeRetirement*YearlySavingsInflated_Over,NA())
Name YearlySavings_Under: IF(PlanYear<=PlanYears,BeforeRetirement*YearlySavingsInflated_Under,NA())

Sheet Retirement planner
B1: Retirement planner
B2: =IF(INDEX(SavingsBalance_RetiredPeriod,PlanYears)>=0,CONCATENATE(ResultsDisplay_Success_1," ",ResultsDisplay_Success_2, " ",ResultsDisplay_Success_3," ",ResultsDisplay_Success_4," ",ResultsDisplay_Success_5),CONCATENATE(ResultsDisplay_Failure_1," ",ResultsDisplay_Failure_2," ",ResultsDisplay_Failure_3," ",ResultsDisplay_Failure_4)) -> CONGRATULATIONS! At age 84, you will have a savings balance of $25,813.
B4: Input
B5: Now | E5: At retirement | H5: Uncertainty
B6: Your current age | D6: 40 | E6: Annual pension benefit ($) | G6: 0 | H6: Investment return uncertainty (%) | J6: 0.02
B7: Annual income ($) | D7: 50000 | E7: Annual pension benefit increases (%) | G7: 0 | H7: Annual savings amount uncertainty (%) | J7: 0
B8: Annual inflation and income increases (%) | D8: 0.03 | E8: Desired retirement age | G8: 65 | H8: Annual savings increases uncertainty (%) | J8: 0
B9: Retirement savings balance ($) | D9: 60000 | E9: Number of years of retirement income | G9: 20 | H9: Annual pension benefit amount uncertainty (%) | J9: 0
B10: Annual savings amount ($) | D10: 15000 | E10: Income replacement (%) | G10: 0.75 | H10: Annual pension benefit increases uncertainty (%) | J10: 0
B11: Annual savings increases (%) | D11: 0 | E11: Investment return (%) | G11: 0.0625
B12: Investment return (%) | D12: 0.0625
B13: Chart details
B14: Age | C14: Salary | D14: Balance | E14: Interest | F14: Yearly savings | G14: Desired retirement income | H14: Pension income | I14: Year ending balance | J14: Notes
B15: =IFERROR(Calculations!B15,"") -> 40 | C15: =IFERROR(Calculations!C15,"") -> 50000 | D15: =IFERROR(Calculations!D15,"") -> 60000 | E15: =IFERROR(Calculations!E15,"") -> 3750 | F15: =IFERROR(Calculations!F15,"") -> 15000 | G15: =IFERROR(Calculations!G15,"") -> 0 | H15: =IFERROR(Calculations!H15,"") -> 0 | I15: =IFERROR(Calculations!I15,"") -> 78750
B16: =IFERROR(Calculations!B16,"") -> 41 | C16: =IFERROR(Calculations!C16,"") -> 51500 | D16: =IFERROR(Calculations!D16,"") -> 78750 | E16: =IFERROR(Calculations!E16,"") -> 4921.875 | F16: =IFERROR(Calculations!F16,"") -> 15000 | G16: =IFERROR(Calculations!G16,"") -> 0 | H16: =IFERROR(Calculations!H16,"") -> 0 | I16: =IFERROR(Calculations!I16,"") -> 98671.875
B17: =IFERROR(Calculations!B17,"") -> 42 | C17: =IFERROR(Calculations!C17,"") -> 53045 | D17: =IFERROR(Calculations!D17,"") -> 98671.875 | E17: =IFERROR(Calculations!E17,"") -> 6166.9922 | F17: =IFERROR(Calculations!F17,"") -> 15000 | G17: =IFERROR(Calculations!G17,"") -> 0 | H17: =IFERROR(Calculations!H17,"") -> 0 | I17: =IFERROR(Calculations!I17,"") -> 119838.87
B18: =IFERROR(Calculations!B18,"") -> 43 | C18: =IFERROR(Calculations!C18,"") -> 54636.35 | D18: =IFERROR(Calculations!D18,"") -> 119838.87 | E18: =IFERROR(Calculations!E18,"") -> 7489.9292 | F18: =IFERROR(Calculations!F18,"") -> 15000 | G18: =IFERROR(Calculations!G18,"") -> 0 | H18: =IFERROR(Calculations!H18,"") -> 0 | I18: =IFERROR(Calculations!I18,"") -> 142328.8
B19: =IFERROR(Calculations!B19,"") -> 44 | C19: =IFERROR(Calculations!C19,"") -> 56275.44 | D19: =IFERROR(Calculations!D19,"") -> 142328.8 | E19: =IFERROR(Calculations!E19,"") -> 8895.5498 | F19: =IFERROR(Calculations!F19,"") -> 15000 | G19: =IFERROR(Calculations!G19,"") -> 0 | H19: =IFERROR(Calculations!H19,"") -> 0 | I19: =IFERROR(Calculations!I19,"") -> 166224.35
B20: =IFERROR(Calculations!B20,"") -> 45 | C20: =IFERROR(Calculations!C20,"") -> 57963.704 | D20: =IFERROR(Calculations!D20,"") -> 166224.35 | E20: =IFERROR(Calculations!E20,"") -> 10389.022 | F20: =IFERROR(Calculations!F20,"") -> 15000 | G20: =IFERROR(Calculations!G20,"") -> 0 | H20: =IFERROR(Calculations!H20,"") -> 0 | I20: =IFERROR(Calculations!I20,"") -> 191613.37
B21: =IFERROR(Calculations!B21,"") -> 46 | C21: =IFERROR(Calculations!C21,"") -> 59702.615 | D21: =IFERROR(Calculations!D21,"") -> 191613.37 | E21: =IFERROR(Calculations!E21,"") -> 11975.835 | F21: =IFERROR(Calculations!F21,"") -> 15000 | G21: =IFERROR(Calculations!G21,"") -> 0 | H21: =IFERROR(Calculations!H21,"") -> 0 | I21: =IFERROR(Calculations!I21,"") -> 218589.2
B22: =IFERROR(Calculations!B22,"") -> 47 | C22: =IFERROR(Calculations!C22,"") -> 61493.693 | D22: =IFERROR(Calculations!D22,"") -> 218589.2 | E22: =IFERROR(Calculations!E22,"") -> 13661.825 | F22: =IFERROR(Calculations!F22,"") -> 15000 | G22: =IFERROR(Calculations!G22,"") -> 0 | H22: =IFERROR(Calculations!H22,"") -> 0 | I22: =IFERROR(Calculations!I22,"") -> 247251.03
B23: =IFERROR(Calculations!B23,"") -> 48 | C23: =IFERROR(Calculations!C23,"") -> 63338.504 | D23: =IFERROR(Calculations!D23,"") -> 247251.03 | E23: =IFERROR(Calculations!E23,"") -> 15453.189 | F23: =IFERROR(Calculations!F23,"") -> 15000 | G23: =IFERROR(Calculations!G23,"") -> 0 | H23: =IFERROR(Calculations!H23,"") -> 0 | I23: =IFERROR(Calculations!I23,"") -> 277704.22
B24: =IFERROR(Calculations!B24,"") -> 49 | C24: =IFERROR(Calculations!C24,"") -> 65238.659 | D24: =IFERROR(Calculations!D24,"") -> 277704.22 | E24: =IFERROR(Calculations!E24,"") -> 17356.514 | F24: =IFERROR(Calculations!F24,"") -> 15000 | G24: =IFERROR(Calculations!G24,"") -> 0 | H24: =IFERROR(Calculations!H24,"") -> 0 | I24: =IFERROR(Calculations!I24,"") -> 310060.73
B25: =IFERROR(Calculations!B25,"") -> 50 | C25: =IFERROR(Calculations!C25,"") -> 67195.819 | D25: =IFERROR(Calculations!D25,"") -> 310060.73 | E25: =IFERROR(Calculations!E25,"") -> 19378.796 | F25: =IFERROR(Calculations!F25,"") -> 15000 | G25: =IFERROR(Calculations!G25,"") -> 0 | H25: =IFERROR(Calculations!H25,"") -> 0 | I25: =IFERROR(Calculations!I25,"") -> 344439.53
B26: =IFERROR(Calculations!B26,"") -> 51 | C26: =IFERROR(Calculations!C26,"") -> 69211.694 | D26: =IFERROR(Calculations!D26,"") -> 344439.53 | E26: =IFERROR(Calculations!E26,"") -> 21527.47 | F26: =IFERROR(Calculations!F26,"") -> 15000 | G26: =IFERROR(Calculations!G26,"") -> 0 | H26: =IFERROR(Calculations!H26,"") -> 0 | I26: =IFERROR(Calculations!I26,"") -> 380967
... B59: =IFERROR(Calculations!B59,"") -> 84 | C59: =IFERROR(Calculations!C59,"") -> 0 | D59: =IFERROR(Calculations!D59,"") -> 153874.92 | E59: =IFERROR(Calculations!E59,"") -> 9617.1825 | F59: =IFERROR(Calculations!F59,"") -> 0 | G59: =IFERROR(Calculations!G59,"") -> 137679.46 | H59: =IFERROR(Calculations!H59,"") -> 0 | I59: =IFERROR(Calculations!I59,"") -> 25812.641

Sheet Calculations
B1: Calculations
B2: This sheet should remain hidden. Any modifications may result in errors in the Retirement Planner.
F3: {=INDEX(B15:B114,MATCH(MIN(IF(ISNUMBER(SavingsBalance_RetiredPeriod),IF((SavingsBalance_RetiredPeriod>0),SavingsBalance_RetiredPeriod))),SavingsBalance_RetiredPeriod,0))} -> 84 | G3: Failure Template: | I3: Oops. This plan will only provide income to age [AGE]. You'll need to make some modifications.
E4: =TEXT(INDEX(SavingsBalance_RetiredPeriod,PlanYears),"$#,###") -> $25,813 | F4: =YourCurrentAge+PlanYears-1 -> 84 | G4: Success Template: | I4: Congratulations! Your plan seems to work. At age [AGE], you will still have a savings balance of [BALANCE].
F6: =INDEX($F$3:$F$4,(INDEX(SavingsBalance_RetiredPeriod,PlanYears)>0)+1) -> 84 | G6: Failure display: | I6: =REPT(SUBSTITUTE(SUBSTITUTE(I3,"[AGE]",$F$6),"[BALANCE]",$E$4),INDEX(SavingsBalance_RetiredPeriod,PlanYears)<0)
F7: =INDEX($F$3:$F$4,(INDEX(SavingsBalance_RetiredPeriod,PlanYears)>0)+1) -> 84 | G7: Success display: | I7: =REPT(SUBSTITUTE(SUBSTITUTE(I4,"[AGE]",$F$6),"[BALANCE]",$E$4),INDEX(SavingsBalance_RetiredPeriod,PlanYears)>=0) -> Congratulations! Your plan seems to work. At age 84, you will still have a savings balance of $25,813.
D8: Success: | E8: =INDEX(SavingsBalance_RetiredPeriod,PlanYears)>=0 -> TRUE | G8: Success | I8: Failure
F9: 1 | G9: =REPT("CONGRATULATIONS!",Success) -> CONGRATULATIONS! | I9: =REPT("OOPS!",Success=FALSE)
F10: 2 | G10: =REPT("At age",Success) -> At age | I10: =REPT("This plan will only provide income up to age",Success=FALSE)
F11: 3 | G11: =REPT(YourCurrentAge+PlanYears-1 & ",",Success) -> 84, | I11: =REPT(F3 & ".",Success=FALSE)
F12: 4 | G12: =REPT("you will have a savings balance of",Success) -> you will have a savings balance of | I12: =REPT("You'll need to make adjustments.",Success=FALSE)
F13: 5 | G13: =REPT(TEXT(INDEX(SavingsBalance_RetiredPeriod,PlanYears),"$#,###."),Success) -> $25,813.
B14: Age | C14: Salary | D14: Balance | E14: Interest | F14: Yearly savings | G14: Desired retirement income | H14: Pension income | I14: End balance | L14: Balance | M14: Interest | N14: Yearly savings | O14: Desired retirement income | P14: Pension income | Q14: End balance | T14: Balance | U14: Interest | V14: Yearly Savings | W14: Desired Retirement Income | X14: Pension Income | Y14: End Balance | AB14: Saving | AC14: Retired | AF14: Uncertainty
B15: =Age -> 40 | C15: =CurrentAnnualIncome -> 50000 | D15: =CurrentRetirementSavingsBalance -> 60000 | E15: =Interest -> 3750 | F15: =CurrentAnnualSavingsAmount -> 15000 | G15: =DesiredRetirementIncome -> 0 | H15: =PensionIncome -> 0 | I15: =EndBalance -> 78750 | L15: =CurrentRetirementSavingsBalance -> 60000 | M15: =Interest_Under -> 3150 | N15: =CurrentAnnualSavingsAmount_Under -> 15000 | O15: =DesiredRetirementIncome -> 0 | P15: =PensionIncome_Under -> 0 | Q15: =EndBalance -> 78150 | T15: =CurrentRetirementSavingsBalance -> 60000 | U15: =Interest_Over -> 4350 | V15: =CurrentAnnualSavingsAmount_Over -> 15000 | W15: =DesiredRetirementIncome -> 0 | X15: =PensionIncome_Over -> 0 | Y15: =EndBalance -> 79350 | AB15: =IF(Calculations!B15<DesiredRetirementAge,I15,NA()) -> 78750 | AC15: =IF(Calculations!B15>=(DesiredRetirementAge-1),I15,NA()) -> #N/A | AF15: =Y15-Q15 -> 1200
B16: =Age -> 41 | C16: =Salary -> 51500 | D16: =Balance -> 78750 | E16: =Interest -> 4921.875 | F16: =YearlySavings -> 15000 | G16: =DesiredRetirementIncome -> 0 | H16: =PensionIncome -> 0 | I16: =EndBalance -> 98671.875 | L16: =Balance_Under -> 78150 | M16: =Interest_Under -> 4102.875 | N16: =YearlySavings_Under -> 15000 | O16: =DesiredRetirementIncome -> 0 | P16: =PensionIncome_Under -> 0 | Q16: =EndBalance -> 97252.875 | T16: =Balance_Over -> 79350 | U16: =Interest_Over -> 5752.875 | V16: =YearlySavings_Over -> 15000 | W16: =DesiredRetirementIncome -> 0 | X16: =PensionIncome_Over -> 0 | Y16: =EndBalance -> 100102.88 | AB16: =IF(Calculations!B16<DesiredRetirementAge,I16,NA()) -> 98671.875 | AC16: =IF(Calculations!B16>=(DesiredRetirementAge-1),I16,NA()) -> #N/A | AF16: =Y16-Q16 -> 2850
B17: =Age -> 42 | C17: =Salary -> 53045 | D17: =Balance -> 98671.875 | E17: =Interest -> 6166.9922 | F17: =YearlySavings -> 15000 | G17: =DesiredRetirementIncome -> 0 | H17: =PensionIncome -> 0 | I17: =EndBalance -> 119838.87 | L17: =Balance_Under -> 97252.875 | M17: =Interest_Under -> 5105.7759 | N17: =YearlySavings_Under -> 15000 | O17: =DesiredRetirementIncome -> 0 | P17: =PensionIncome_Under -> 0 | Q17: =EndBalance -> 117358.65 | T17: =Balance_Over -> 100102.88 | U17: =Interest_Over -> 7257.4584 | V17: =YearlySavings_Over -> 15000 | W17: =DesiredRetirementIncome -> 0 | X17: =PensionIncome_Over -> 0 | Y17: =EndBalance -> 122360.33 | AB17: =IF(Calculations!B17<DesiredRetirementAge,I17,NA()) -> 119838.87 | AC17: =IF(Calculations!B17>=(DesiredRetirementAge-1),I17,NA()) -> #N/A | AF17: =Y17-Q17 -> 5001.6825
B18: =Age -> 43 | C18: =Salary -> 54636.35 | D18: =Balance -> 119838.87 | E18: =Interest -> 7489.9292 | F18: =YearlySavings -> 15000 | G18: =DesiredRetirementIncome -> 0 | H18: =PensionIncome -> 0 | I18: =EndBalance -> 142328.8 | L18: =Balance_Under -> 117358.65 | M18: =Interest_Under -> 6161.3292 | N18: =YearlySavings_Under -> 15000 | O18: =DesiredRetirementIncome -> 0 | P18: =PensionIncome_Under -> 0 | Q18: =EndBalance -> 138519.98 | T18: =Balance_Over -> 122360.33 | U18: =Interest_Over -> 8871.1242 | V18: =YearlySavings_Over -> 15000 | W18: =DesiredRetirementIncome -> 0 | X18: =PensionIncome_Over -> 0 | Y18: =EndBalance -> 146231.46 | AB18: =IF(Calculations!B18<DesiredRetirementAge,I18,NA()) -> 142328.8 | AC18: =IF(Calculations!B18>=(DesiredRetirementAge-1),I18,NA()) -> #N/A | AF18: =Y18-Q18 -> 7711.4775
B19: =Age -> 44 | C19: =Salary -> 56275.44 | D19: =Balance -> 142328.8 | E19: =Interest -> 8895.5498 | F19: =YearlySavings -> 15000 | G19: =DesiredRetirementIncome -> 0 | H19: =PensionIncome -> 0 | I19: =EndBalance -> 166224.35 | L19: =Balance_Under -> 138519.98 | M19: =Interest_Under -> 7272.299 | N19: =YearlySavings_Under -> 15000 | O19: =DesiredRetirementIncome -> 0 | P19: =PensionIncome_Under -> 0 | Q19: =EndBalance -> 160792.28 | T19: =Balance_Over -> 146231.46 | U19: =Interest_Over -> 10601.781 | V19: =YearlySavings_Over -> 15000 | W19: =DesiredRetirementIncome -> 0 | X19: =PensionIncome_Over -> 0 | Y19: =EndBalance -> 171833.24 | AB19: =IF(Calculations!B19<DesiredRetirementAge,I19,NA()) -> 166224.35 | AC19: =IF(Calculations!B19>=(DesiredRetirementAge-1),I19,NA()) -> #N/A | AF19: =Y19-Q19 -> 11040.959
B20: =Age -> 45 | C20: =Salary -> 57963.704 | D20: =Balance -> 166224.35 | E20: =Interest -> 10389.022 | F20: =YearlySavings -> 15000 | G20: =DesiredRetirementIncome -> 0 | H20: =PensionIncome -> 0 | I20: =EndBalance -> 191613.37 | L20: =Balance_Under -> 160792.28 | M20: =Interest_Under -> 8441.5947 | N20: =YearlySavings_Under -> 15000 | O20: =DesiredRetirementIncome -> 0 | P20: =PensionIncome_Under -> 0 | Q20: =EndBalance -> 184233.87 | T20: =Balance_Over -> 171833.24 | U20: =Interest_Over -> 12457.91 | V20: =YearlySavings_Over -> 15000 | W20: =DesiredRetirementIncome -> 0 | X20: =PensionIncome_Over -> 0 | Y20: =EndBalance -> 199291.15 | AB20: =IF(Calculations!B20<DesiredRetirementAge,I20,NA()) -> 191613.37 | AC20: =IF(Calculations!B20>=(DesiredRetirementAge-1),I20,NA()) -> #N/A | AF20: =Y20-Q20 -> 15057.274
B21: =Age -> 46 | C21: =Salary -> 59702.615 | D21: =Balance -> 191613.37 | E21: =Interest -> 11975.835 | F21: =YearlySavings -> 15000 | G21: =DesiredRetirementIncome -> 0 | H21: =PensionIncome -> 0 | I21: =EndBalance -> 218589.2 | L21: =Balance_Under -> 184233.87 | M21: =Interest_Under -> 9672.2784 | N21: =YearlySavings_Under -> 15000 | O21: =DesiredRetirementIncome -> 0 | P21: =PensionIncome_Under -> 0 | Q21: =EndBalance -> 208906.15 | T21: =Balance_Over -> 199291.15 | U21: =Interest_Over -> 14448.608 | V21: =YearlySavings_Over -> 15000 | W21: =DesiredRetirementIncome -> 0 | X21: =PensionIncome_Over -> 0 | Y21: =EndBalance -> 228739.76 | AB21: =IF(Calculations!B21<DesiredRetirementAge,I21,NA()) -> 218589.2 | AC21: =IF(Calculations!B21>=(DesiredRetirementAge-1),I21,NA()) -> #N/A | AF21: =Y21-Q21 -> 19833.604
B22: =Age -> 47 | C22: =Salary -> 61493.693 | D22: =Balance -> 218589.2 | E22: =Interest -> 13661.825 | F22: =YearlySavings -> 15000 | G22: =DesiredRetirementIncome -> 0 | H22: =PensionIncome -> 0 | I22: =EndBalance -> 247251.03 | L22: =Balance_Under -> 208906.15 | M22: =Interest_Under -> 10967.573 | N22: =YearlySavings_Under -> 15000 | O22: =DesiredRetirementIncome -> 0 | P22: =PensionIncome_Under -> 0 | Q22: =EndBalance -> 234873.73 | T22: =Balance_Over -> 228739.76 | U22: =Interest_Over -> 16583.632 | V22: =YearlySavings_Over -> 15000 | W22: =DesiredRetirementIncome -> 0 | X22: =PensionIncome_Over -> 0 | Y22: =EndBalance -> 260323.39 | AB22: =IF(Calculations!B22<DesiredRetirementAge,I22,NA()) -> 247251.03 | AC22: =IF(Calculations!B22>=(DesiredRetirementAge-1),I22,NA()) -> #N/A | AF22: =Y22-Q22 -> 25449.664
B23: =Age -> 48 | C23: =Salary -> 63338.504 | D23: =Balance -> 247251.03 | E23: =Interest -> 15453.189 | F23: =YearlySavings -> 15000 | G23: =DesiredRetirementIncome -> 0 | H23: =PensionIncome -> 0 | I23: =EndBalance -> 277704.22 | L23: =Balance_Under -> 234873.73 | M23: =Interest_Under -> 12330.871 | N23: =YearlySavings_Under -> 15000 | O23: =DesiredRetirementIncome -> 0 | P23: =PensionIncome_Under -> 0 | Q23: =EndBalance -> 262204.6 | T23: =Balance_Over -> 260323.39 | U23: =Interest_Over -> 18873.446 | V23: =YearlySavings_Over -> 15000 | W23: =DesiredRetirementIncome -> 0 | X23: =PensionIncome_Over -> 0 | Y23: =EndBalance -> 294196.83 | AB23: =IF(Calculations!B23<DesiredRetirementAge,I23,NA()) -> 277704.22 | AC23: =IF(Calculations!B23>=(DesiredRetirementAge-1),I23,NA()) -> #N/A | AF23: =Y23-Q23 -> 31992.239
B24: =Age -> 49 | C24: =Salary -> 65238.659 | D24: =Balance -> 277704.22 | E24: =Interest -> 17356.514 | F24: =YearlySavings -> 15000 | G24: =DesiredRetirementIncome -> 0 | H24: =PensionIncome -> 0 | I24: =EndBalance -> 310060.73 | L24: =Balance_Under -> 262204.6 | M24: =Interest_Under -> 13765.741 | N24: =YearlySavings_Under -> 15000 | O24: =DesiredRetirementIncome -> 0 | P24: =PensionIncome_Under -> 0 | Q24: =EndBalance -> 290970.34 | T24: =Balance_Over -> 294196.83 | U24: =Interest_Over -> 21329.27 | V24: =YearlySavings_Over -> 15000 | W24: =DesiredRetirementIncome -> 0 | X24: =PensionIncome_Over -> 0 | Y24: =EndBalance -> 330526.1 | AB24: =IF(Calculations!B24<DesiredRetirementAge,I24,NA()) -> 310060.73 | AC24: =IF(Calculations!B24>=(DesiredRetirementAge-1),I24,NA()) -> #N/A | AF24: =Y24-Q24 -> 39555.768
B25: =Age -> 50 | C25: =Salary -> 67195.819 | D25: =Balance -> 310060.73 | E25: =Interest -> 19378.796 | F25: =YearlySavings -> 15000 | G25: =DesiredRetirementIncome -> 0 | H25: =PensionIncome -> 0 | I25: =EndBalance -> 344439.53 | L25: =Balance_Under -> 290970.34 | M25: =Interest_Under -> 15275.943 | N25: =YearlySavings_Under -> 15000 | O25: =DesiredRetirementIncome -> 0 | P25: =PensionIncome_Under -> 0 | Q25: =EndBalance -> 321246.28 | T25: =Balance_Over -> 330526.1 | U25: =Interest_Over -> 23963.143 | V25: =YearlySavings_Over -> 15000 | W25: =DesiredRetirementIncome -> 0 | X25: =PensionIncome_Over -> 0 | Y25: =EndBalance -> 369489.25 | AB25: =IF(Calculations!B25<DesiredRetirementAge,I25,NA()) -> 344439.53 | AC25: =IF(Calculations!B25>=(DesiredRetirementAge-1),I25,NA()) -> #N/A | AF25: =Y25-Q25 -> 48242.968
B26: =Age -> 51 | C26: =Salary -> 69211.694 | D26: =Balance -> 344439.53 | E26: =Interest -> 21527.47 | F26: =YearlySavings -> 15000 | G26: =DesiredRetirementIncome -> 0 | H26: =PensionIncome -> 0 | I26: =EndBalance -> 380967 | L26: =Balance_Under -> 321246.28 | M26: =Interest_Under -> 16865.43 | N26: =YearlySavings_Under -> 15000 | O26: =DesiredRetirementIncome -> 0 | P26: =PensionIncome_Under -> 0 | Q26: =EndBalance -> 353111.71 | T26: =Balance_Over -> 369489.25 | U26: =Interest_Over -> 26787.97 | V26: =YearlySavings_Over -> 15000 | W26: =DesiredRetirementIncome -> 0 | X26: =PensionIncome_Over -> 0 | Y26: =EndBalance -> 411277.22 | AB26: =IF(Calculations!B26<DesiredRetirementAge,I26,NA()) -> 380967 | AC26: =IF(Calculations!B26>=(DesiredRetirementAge-1),I26,NA()) -> #N/A | AF26: =Y26-Q26 -> 58165.509
B27: =Age -> 52 | C27: =Salary -> 71288.044 | D27: =Balance -> 380967 | E27: =Interest -> 23810.437 | F27: =YearlySavings -> 15000 | G27: =DesiredRetirementIncome -> 0 | H27: =PensionIncome -> 0 | I27: =EndBalance -> 419777.43 | L27: =Balance_Under -> 353111.71 | M27: =Interest_Under -> 18538.365 | N27: =YearlySavings_Under -> 15000 | O27: =DesiredRetirementIncome -> 0 | P27: =PensionIncome_Under -> 0 | Q27: =EndBalance -> 386650.07 | T27: =Balance_Over -> 411277.22 | U27: =Interest_Over -> 29817.598 | V27: =YearlySavings_Over -> 15000 | W27: =DesiredRetirementIncome -> 0 | X27: =PensionIncome_Over -> 0 | Y27: =EndBalance -> 456094.82 | AB27: =IF(Calculations!B27<DesiredRetirementAge,I27,NA()) -> 419777.43 | AC27: =IF(Calculations!B27>=(DesiredRetirementAge-1),I27,NA()) -> #N/A | AF27: =Y27-Q27 -> 69444.742
... B114: =Age -> #N/A | C114: =Salary -> #N/A | D114: =Balance -> #N/A | E114: =Interest -> #N/A | F114: =YearlySavings -> #N/A | G114: =DesiredRetirementIncome -> #N/A | H114: =PensionIncome -> #N/A | I114: =EndBalance -> #N/A | L114: =Balance_Under -> #N/A | M114: =Interest_Under -> #N/A | N114: =YearlySavings_Under -> #N/A | O114: =DesiredRetirementIncome -> #N/A | P114: =PensionIncome_Under -> #N/A | Q114: =EndBalance -> #N/A | T114: =Balance_Over -> #N/A | U114: =Interest_Over -> #N/A | V114: =YearlySavings_Over -> #N/A | W114: =DesiredRetirementIncome -> #N/A | X114: =PensionIncome_Over -> #N/A | Y114: =EndBalance -> #N/A | AB114: =IF(Calculations!B114<DesiredRetirementAge,I114,NA()) -> #N/A | AC114: =IF(Calculations!B114>=(DesiredRetirementAge-1),I114,NA()) -> #N/A | AF114: =Y114-Q114 -> #N/A
